MANIFEST.in
README.rst
setup.cfg
setup.py
docs/.DS_Store
docs/CONTRIBUTORS.rst
docs/HISTORY.rst
docs/INSTALL.txt
docs/LICENSE.GPL
docs/LICENSE.txt
izug/.DS_Store
izug/__init__.py
izug.seantis.dir.events.egg-info/PKG-INFO
izug.seantis.dir.events.egg-info/SOURCES.txt
izug.seantis.dir.events.egg-info/dependency_links.txt
izug.seantis.dir.events.egg-info/entry_points.txt
izug.seantis.dir.events.egg-info/namespace_packages.txt
izug.seantis.dir.events.egg-info/not-zip-safe
izug.seantis.dir.events.egg-info/requires.txt
izug.seantis.dir.events.egg-info/top_level.txt
izug/seantis/__init__.py
izug/seantis/dir/__init__.py
izug/seantis/dir/events/__init__.py
izug/seantis/dir/events/configure.zcml
izug/seantis/dir/events/guard.py
izug/seantis/dir/events/import.py
izug/seantis/dir/events/setuphandlers.py
izug/seantis/dir/events/sync.sh
izug/seantis/dir/events/locales/izug.seantis.dir.events.pot
izug/seantis/dir/events/locales/de/LC_MESSAGES/izug.seantis.dir.events.po
izug/seantis/dir/events/profiles/default/metadata.xml