Metadata-Version: 1.1
Name: izug.seantis.dir.events
Version: 1.0rc1
Summary: Integration of seantis.dir.events into izug.
Home-page: https://github.com/seantis/izug.seantis.dir.events
Author: Seantis GmbH
Author-email: info@seantis.ch
License: GPL
Platform: UNKNOWN
Classifier: Framework :: Plone
Classifier: Programming Language :: Python
